keras_sklearn_multihead_classifier/__init__.py
keras_sklearn_multihead_classifier/estimator.py
keras_sklearn_multihead_classifier-1.2.dist-info/METADATA
keras_sklearn_multihead_classifier-1.2.dist-info/WHEEL
keras_sklearn_multihead_classifier-1.2.dist-info/top_level.txt
keras_sklearn_multihead_classifier-1.2.dist-info/RECORD
