Metadata-Version: 2.1
Name: keras-sklearn-multihead-classifier
Version: 1.2
Summary: Keras Sklearn Multihead Classifier
Home-page: UNKNOWN
Author: Moshe Berchansky
Author-email: screedo1997@gmail.com
License: UNKNOWN
Platform: UNKNOWN
